Metadata-Version: 2.4
Name: sidan-binance-py
Version: 0.0.2
Summary: Modern, lightweight Python SDK for Binance public API - Fork of binance-connector with enhanced tooling and packaging
Project-URL: Homepage, https://github.com/sidan-lab/sidan-binance-py
Project-URL: Repository, https://github.com/sidan-lab/sidan-binance-py
Project-URL: Documentation, https://sidan-lab.github.io/sidan-binance-py/
Project-URL: Bug Tracker, https://github.com/sidan-lab/sidan-binance-py/issues
Project-URL: Original Connector, https://github.com/binance/binance-connector-python
Author: Binance
Author-email: Fork Maintainer <maintainer@example.com>
License: MIT
License-File: LICENSE.md
Keywords: Binance,Cryptocurrency,Public API,SDK,Trading,WebSocket
Classifier: Development Status :: 5 - Production/Stable
Classifier: Intended Audience :: Developers
Classifier: Intended Audience :: Financial and Insurance Industry
Classifier: License :: OSI Approved :: MIT License
Classifier: Programming Language :: Python :: 3.8
Classifier: Programming Language :: Python :: 3.9
Classifier: Programming Language :: Python :: 3.10
Classifier: Programming Language :: Python :: 3.11
Classifier: Programming Language :: Python :: 3.12
Classifier: Topic :: Internet :: WWW/HTTP
Classifier: Topic :: Office/Business :: Financial :: Investment
Classifier: Topic :: Software Development :: Libraries :: Python Modules
Requires-Python: >=3.8
Requires-Dist: pycryptodome>=3.15.0
Requires-Dist: requests>=2.31.0
Requires-Dist: websocket-client>=1.6.3
